[
  {
    "id": "d78057f8780c",
    "timestamp": "2026-04-18T10:33:06.506605+00:00",
    "schema_version": "inductive.v9",
    "domain": "social psychology",
    "contrast_label": "association of social class with warmth and competence",
    "labels": {
      "X": "wealthy people",
      "Y": "poor people",
      "A": "warmth",
      "B": "competence"
    },
    "canonical_keys": {
      "X": "people|wealthy",
      "Y": "people|poor",
      "A": "warmth",
      "B": "competence"
    },
    "effect_size": 0.10535135425634955,
    "p_value": 0.74571,
    "n": {
      "X": 20,
      "Y": 20,
      "A": 20,
      "B": 20
    },
    "n_permutations": 100000,
    "exact": false,
    "words": {
      "X_used": [
        "rich",
        "affluent",
        "opulent",
        "prosperous",
        "wealthy",
        "privileged",
        "elite",
        "moneyed",
        "upscale",
        "plutocrat",
        "capitalist",
        "bourgeois",
        "magnate",
        "tycoon",
        "millionaire",
        "billionaire",
        "aristocrat",
        "patrician",
        "mogul",
        "lord"
      ],
      "Y_used": [
        "poor",
        "needy",
        "broke",
        "impoverished",
        "destitute",
        "underprivileged",
        "penniless",
        "indigent",
        "disadvantaged",
        "pauper",
        "beggar",
        "proletariat",
        "struggling",
        "bankrupt",
        "insolvent",
        "peasant",
        "vagrant",
        "nomad",
        "urchin",
        "serf"
      ],
      "A_used": [
        "kind",
        "friendly",
        "warm",
        "gentle",
        "caring",
        "sweet",
        "helpful",
        "amiable",
        "cordial",
        "affectionate",
        "soft",
        "nice",
        "sympathetic",
        "tender",
        "loving",
        "pleasant",
        "gracious",
        "benevolent",
        "empathetic",
        "welcoming"
      ],
      "B_used": [
        "smart",
        "capable",
        "skilled",
        "efficient",
        "expert",
        "bright",
        "intelligent",
        "adept",
        "proficient",
        "competent",
        "clever",
        "sharp",
        "talented",
        "effective",
        "masterful",
        "organized",
        "disciplined",
        "logical",
        "rational",
        "strategic"
      ],
      "X_dropped": [],
      "Y_dropped": [],
      "A_dropped": [],
      "B_dropped": []
    },
    "prediction": {
      "expected_direction": "negative",
      "confidence": "medium",
      "rationale": "The Stereotype Content Model suggests high-status groups are perceived as competent but cold, while low-status groups are seen as warm but incompetent."
    },
    "interpretive_paragraph": "",
    "interpretive_fired": false,
    "config": {
      "embedding_backend": "gensim:dolma.2024.300d.kv",
      "proposer_model": "gemma4:31b-it-q8_0",
      "proposer_mode": "well-studied",
      "thinking_style": "gemma4",
      "thinking_effort": "on",
      "history_size_seen": 0,
      "cooled_domains_at_proposal": [],
      "sampling": {
        "temperature": 1.0,
        "top_p": 0.95,
        "top_k": 64,
        "num_ctx": 32768,
        "repeat_penalty": 1.0
      }
    }
  },
  {
    "id": "38b851310b23",
    "timestamp": "2026-04-18T10:37:31.493237+00:00",
    "schema_version": "inductive.v9",
    "domain": "humanities",
    "contrast_label": "scientists vs philosophers regarding optimism vs pessimism",
    "labels": {
      "X": "scientists",
      "Y": "philosophers",
      "A": "optimism",
      "B": "pessimism"
    },
    "canonical_keys": {
      "X": "scientists",
      "Y": "philosophers",
      "A": "optimism",
      "B": "pessimism"
    },
    "effect_size": 1.4427732807380722,
    "p_value": 0.0,
    "n": {
      "X": 20,
      "Y": 20,
      "A": 20,
      "B": 20
    },
    "n_permutations": 100000,
    "exact": false,
    "words": {
      "X_used": [
        "biologist",
        "chemist",
        "physicist",
        "geologist",
        "astronomer",
        "botanist",
        "zoologist",
        "researcher",
        "analyst",
        "technician",
        "expert",
        "investigator",
        "clinician",
        "pathologist",
        "geneticist",
        "mathematician",
        "oceanographer",
        "meteorologist",
        "epidemiologist",
        "crystallographer"
      ],
      "Y_used": [
        "thinker",
        "ethicist",
        "logician",
        "metaphysician",
        "epistemologist",
        "sage",
        "humanist",
        "dialectician",
        "rationalist",
        "idealist",
        "skeptic",
        "stoic",
        "cynic",
        "sophist",
        "moralist",
        "ontologist",
        "phenomenologist",
        "existentialist",
        "meditator",
        "contemplative"
      ],
      "A_used": [
        "hopeful",
        "positive",
        "bright",
        "sanguine",
        "upbeat",
        "cheerful",
        "confident",
        "expectant",
        "sunny",
        "rosy",
        "promising",
        "bullish",
        "eager",
        "optimistic",
        "radiant",
        "glowing",
        "idealistic",
        "certain",
        "assured",
        "buoyant"
      ],
      "B_used": [
        "bleak",
        "dark",
        "cynical",
        "gloomy",
        "hopeless",
        "dour",
        "cheerless",
        "grim",
        "morose",
        "despondent",
        "skeptical",
        "defeatist",
        "pessimistic",
        "shadowy",
        "somber",
        "melancholy",
        "fatalistic",
        "wary",
        "distrustful",
        "dismal"
      ],
      "X_dropped": [],
      "Y_dropped": [],
      "A_dropped": [],
      "B_dropped": []
    },
    "prediction": {
      "expected_direction": "positive",
      "confidence": "medium",
      "rationale": "The corpus may associate the empirical progress of science with optimism and the existential inquiries of philosophy with pessimism."
    },
    "interpretive_paragraph": "The WEAT result shows that scientists are more strongly associated with optimism than philosophers are. This indicates that the corpus uses vocabulary related to scientists in closer proximity to optimism, while philosophers are more closely linked to pessimism. This pattern likely exists because web text often frames scientific work through the lens of progress and discovery, whereas philosophy is frequently discussed in the context of existential questioning or critical skepticism. A social scientist might find this interesting because it reveals how professional identities are emotionally coded in public discourse. It suggests that society implicitly associates the empirical pursuit of knowledge with positive outcomes and the conceptual pursuit of wisdom with more somber reflections.",
    "interpretive_fired": true,
    "config": {
      "embedding_backend": "gensim:dolma.2024.300d.kv",
      "proposer_model": "gemma4:31b-it-q8_0",
      "proposer_mode": "novel",
      "thinking_style": "gemma4",
      "thinking_effort": "on",
      "history_size_seen": 1,
      "cooled_domains_at_proposal": [],
      "sampling": {
        "temperature": 1.0,
        "top_p": 0.95,
        "top_k": 64,
        "num_ctx": 32768,
        "repeat_penalty": 1.0
      }
    }
  },
  {
    "id": "1ac6eba02e3c",
    "timestamp": "2026-04-18T10:41:49.728608+00:00",
    "schema_version": "inductive.v9",
    "domain": "social psychology",
    "contrast_label": "gender associations with agency and communion",
    "labels": {
      "X": "men",
      "Y": "women",
      "A": "agency",
      "B": "communion"
    },
    "canonical_keys": {
      "X": "men",
      "Y": "women",
      "A": "agency",
      "B": "communion"
    },
    "effect_size": 0.8989933591393998,
    "p_value": 0.00112,
    "n": {
      "X": 25,
      "Y": 25,
      "A": 25,
      "B": 25
    },
    "n_permutations": 100000,
    "exact": false,
    "words": {
      "X_used": [
        "man",
        "male",
        "guy",
        "father",
        "brother",
        "son",
        "husband",
        "gentleman",
        "boy",
        "patriarch",
        "sire",
        "lord",
        "king",
        "uncle",
        "nephew",
        "grandpa",
        "grandson",
        "lad",
        "fellow",
        "mister",
        "sir",
        "dude",
        "bloke",
        "pop",
        "dad"
      ],
      "Y_used": [
        "woman",
        "female",
        "girl",
        "mother",
        "sister",
        "daughter",
        "wife",
        "lady",
        "matriarch",
        "dame",
        "queen",
        "aunt",
        "niece",
        "grandma",
        "granddaughter",
        "lass",
        "maiden",
        "mistress",
        "miss",
        "gal",
        "madam",
        "belle",
        "mom",
        "mama",
        "mummy"
      ],
      "A_used": [
        "ambitious",
        "dominant",
        "competitive",
        "assertive",
        "forceful",
        "decisive",
        "active",
        "bold",
        "driven",
        "commanding",
        "powerful",
        "strong",
        "independent",
        "proud",
        "tough",
        "rugged",
        "firm",
        "stern",
        "direct",
        "resolute",
        "vigorous",
        "hardy",
        "potent",
        "eager",
        "daring"
      ],
      "B_used": [
        "nurturing",
        "gentle",
        "caring",
        "soft",
        "sweet",
        "helpful",
        "empathetic",
        "warm",
        "kind",
        "affectionate",
        "tender",
        "loving",
        "supportive",
        "peaceful",
        "patient",
        "modest",
        "sensitive",
        "friendly",
        "amiable",
        "compassionate",
        "mild",
        "cordial",
        "serene",
        "mellow",
        "cozy"
      ],
      "X_dropped": [],
      "Y_dropped": [],
      "A_dropped": [],
      "B_dropped": []
    },
    "prediction": null,
    "interpretive_paragraph": "The results indicate that words associated with men are more strongly linked to agency than words associated with women are, who instead show a stronger relative association with communion. This pattern likely reflects the prevalence of traditional gender stereotypes in web text, where men are more frequently depicted in roles of leadership and independence while women are characterized by their nurturing or supportive capacities. A social scientist studying this domain would find this significant because it illustrates how implicit biases regarding gender are codified in the large-scale linguistic data that shape contemporary communication. Such a finding reveals how language encodes a social structure that distributes instrumental and expressive attributes unevenly across gender categories.",
    "interpretive_fired": true,
    "config": {
      "embedding_backend": "gensim:dolma.2024.300d.kv",
      "proposer_model": "gemma4:31b-it-q8_0",
      "proposer_mode": "well-studied",
      "thinking_style": "gemma4",
      "thinking_effort": "on",
      "history_size_seen": 2,
      "cooled_domains_at_proposal": [],
      "sampling": {
        "temperature": 1.0,
        "top_p": 0.95,
        "top_k": 64,
        "num_ctx": 32768,
        "repeat_penalty": 1.0
      }
    }
  },
  {
    "id": "488a5938d678",
    "timestamp": "2026-04-18T10:48:13.528163+00:00",
    "schema_version": "inductive.v9",
    "domain": "social psychology",
    "contrast_label": "young people vs older people × irony vs sincerity",
    "labels": {
      "X": "young people",
      "Y": "older people",
      "A": "irony",
      "B": "sincerity"
    },
    "canonical_keys": {
      "X": "people|young",
      "Y": "older|people",
      "A": "irony",
      "B": "sincerity"
    },
    "effect_size": -0.5817729039934708,
    "p_value": 0.0691,
    "n": {
      "X": 20,
      "Y": 20,
      "A": 25,
      "B": 25
    },
    "n_permutations": 100000,
    "exact": false,
    "words": {
      "X_used": [
        "recruit",
        "youth",
        "sophomore",
        "teen",
        "youngster",
        "child",
        "neonate",
        "undergrad",
        "pupil",
        "student",
        "freshman",
        "baby",
        "protégé",
        "adolescent",
        "toddler",
        "junior",
        "fledgling",
        "rookie",
        "apprentice",
        "trainee"
      ],
      "Y_used": [
        "elder",
        "senior",
        "pensioner",
        "retiree",
        "veteran",
        "patriarch",
        "matriarch",
        "ancestor",
        "grandparent",
        "grandmother",
        "grandfather",
        "matron",
        "octogenarian",
        "nonagenarian",
        "centenarian",
        "oldtimer",
        "dean",
        "sage",
        "emeritus",
        "predecessor"
      ],
      "A_used": [
        "ironic",
        "sarcastic",
        "cynical",
        "sardonic",
        "wry",
        "mocking",
        "satirical",
        "facetious",
        "detached",
        "snarky",
        "playful",
        "biting",
        "caustic",
        "dry",
        "oblique",
        "indirect",
        "nuanced",
        "clever",
        "witty",
        "teasing",
        "droll",
        "bantering",
        "scoffing",
        "sneering",
        "jeering"
      ],
      "B_used": [
        "sincere",
        "earnest",
        "honest",
        "genuine",
        "direct",
        "frank",
        "candid",
        "heartfelt",
        "pure",
        "naive",
        "straightforward",
        "open",
        "trusting",
        "plain",
        "serious",
        "solemn",
        "grave",
        "devout",
        "faithful",
        "steady",
        "authentic",
        "truthful",
        "simple",
        "unvarnished",
        "transparent"
      ],
      "X_dropped": [],
      "Y_dropped": [],
      "A_dropped": [],
      "B_dropped": []
    },
    "prediction": {
      "expected_direction": "positive",
      "confidence": "medium",
      "rationale": "Modern digital communication styles associated with younger generations often emphasize irony and snark compared to the perceived earnestness of older generations."
    },
    "interpretive_paragraph": "",
    "interpretive_fired": false,
    "config": {
      "embedding_backend": "gensim:dolma.2024.300d.kv",
      "proposer_model": "gemma4:31b-it-q8_0",
      "proposer_mode": "novel",
      "thinking_style": "gemma4",
      "thinking_effort": "on",
      "history_size_seen": 3,
      "cooled_domains_at_proposal": [],
      "sampling": {
        "temperature": 1.0,
        "top_p": 0.95,
        "top_k": 64,
        "num_ctx": 32768,
        "repeat_penalty": 1.0
      }
    }
  }
]